COPYING
MANIFEST.in
README.rst
setup.py
docs/Makefile
docs/changelog.rst
docs/conf.py
docs/index.rst
docs/urwid-logo.png
docs/examples/bigtext.py
docs/examples/bigtext.py.xdotool
docs/examples/bigtext1.png
docs/examples/bigtext2.png
docs/examples/bigtext3.png
docs/examples/browse.py
docs/examples/browse.py.xdotool
docs/examples/browse1.png
docs/examples/browse2.png
docs/examples/edit.py
docs/examples/edit.py.xdotool
docs/examples/edit1.png
docs/examples/edit2.png
docs/examples/graph.py
docs/examples/graph.py.xdotool
docs/examples/graph1.png
docs/examples/graph2.png
docs/examples/index.rst
docs/examples/palette_test.py
docs/examples/palette_test.py.xdotool
docs/examples/palette_test1.png
docs/examples/palette_test2.png
docs/examples/pop_up.py
docs/examples/pop_up.py.xdotool
docs/examples/pop_up1.png
docs/examples/pop_up2.png
docs/examples/real_browse.py
docs/examples/real_edit.py
docs/examples/subproc.py
docs/examples/subproc.py.xdotool
docs/examples/subproc1.png
docs/examples/subproc2.png
docs/examples/subproc2.py
docs/examples/tour.py
docs/examples/tour.py.xdotool
docs/examples/tour1.png
docs/examples/tour2.png
docs/manual/bright_combinations.py
docs/manual/bright_combinations.py.xdotool
docs/manual/bright_combinations1.png
docs/manual/canvascache.rst
docs/manual/displayattributes.rst
docs/manual/displaymodules.rst
docs/manual/encodings.rst
docs/manual/index.rst
docs/manual/mainloop.rst
docs/manual/overview.rst
docs/manual/safe_combinations.py
docs/manual/safe_combinations.py.xdotool
docs/manual/safe_combinations1.png
docs/manual/textlayout.rst
docs/manual/userinput.rst
docs/manual/wanat.py
docs/manual/wanat_multi.py
docs/manual/wcur1.py
docs/manual/wcur2.py
docs/manual/widgets.rst
docs/manual/wmod.py
docs/manual/wsel.py
docs/manual/images/display_modules.png
docs/manual/images/introduction.png
docs/manual/images/urwid_widgets_1.png
docs/manual/images/urwid_widgets_2.png
docs/manual/images/widget_layout.png
docs/reference/attrspec.rst
docs/reference/canvas.rst
hangups_urwid.egg-info/PKG-INFO
hangups_urwid.egg-info/SOURCES.txt
hangups_urwid.egg-info/dependency_links.txt
hangups_urwid.egg-info/not-zip-safe
hangups_urwid.egg-info/top_level.txt
